websockets_proxy/__init__.py
websockets_proxy/websockets_proxy.py
websockets_proxy-0.1.1.dist-info/METADATA
websockets_proxy-0.1.1.dist-info/WHEEL
websockets_proxy-0.1.1.dist-info/licenses/LICENSE
websockets_proxy-0.1.1.dist-info/RECORD
