Metadata-Version: 2.1
Name: websockets_proxy
Version: 0.1.1
Summary: Connect to websockets through a proxy server.
Project-URL: Homepage, https://github.com/racinette/websockets_proxy
Project-URL: Issues, https://github.com/racinette/websockets_proxy/issues
Author-email: Andrei Karavatski <verolomnyy@gmail.com>
Maintainer-email: Andrei Karavatski <verolomnyy@gmail.com>
License: MIT License
License-File: LICENSE
Keywords: async,http,http proxy,https,socks4,socks5,websocket client,websocket proxy,websockets,websockets proxy,ws,wss
Classifier: Development Status :: 5 - Production/Stable
Classifier: Framework :: AsyncIO
Classifier: Intended Audience :: Developers
Classifier: License :: OSI Approved :: MIT License
Classifier: Operating System :: OS Independent
Classifier: Programming Language :: Python
Classifier: Programming Language :: Python :: 3
Classifier: Programming Language :: Python :: 3 :: Only
Classifier: Programming Language :: Python :: 3.8
Classifier: Programming Language :: Python :: 3.9
Classifier: Programming Language :: Python :: 3.10
Classifier: Programming Language :: Python :: 3.11
Classifier: Programming Language :: Python :: 3.12
Classifier: Programming Language :: Python :: 3.13
Classifier: Topic :: Internet :: Proxy Servers
Classifier: Topic :: Internet :: WWW/HTTP
Classifier: Topic :: Software Development :: Libraries
Classifier: Topic :: Software Development :: Libraries :: Python Modules
Classifier: Typing :: Typed
Requires-Python: >=3.8
Requires-Dist: python-socks[asyncio]==2.4.4
Requires-Dist: websockets
